deplatformer_webapp/__init__.py
deplatformer_webapp/app.py
deplatformer_webapp/cli.py
deplatformer_webapp/config.py
deplatformer_webapp/forms/_init_.py
deplatformer_webapp/forms/facebook_forms.py
deplatformer_webapp/helpers/__init__.py
deplatformer_webapp/helpers/db.py
deplatformer_webapp/helpers/facebook_helpers.py
deplatformer_webapp/helpers/filecoin_helpers.py
deplatformer_webapp/helpers/ipfs.py
deplatformer_webapp/lib/ipfshttpclient-0.7.0a1-py3-none-any.whl
deplatformer_webapp/migrations/README
deplatformer_webapp/migrations/alembic.ini
deplatformer_webapp/migrations/env.py
deplatformer_webapp/migrations/script.py.mako
deplatformer_webapp/migrations/versions/c59b91455b84_.py
deplatformer_webapp/models/filecoin_models.py
deplatformer_webapp/models/user_models.py
deplatformer_webapp/scripts.py
deplatformer_webapp/services/ipfs.py
deplatformer_webapp/static/assets/Facebook/Facebook-step1a.png
deplatformer_webapp/static/assets/Facebook/Facebook-step1b.png
deplatformer_webapp/static/assets/Facebook/Facebook-step1c.png
deplatformer_webapp/static/assets/Facebook/Facebook-step1d.png
deplatformer_webapp/static/assets/Facebook/Facebook-step1e.png
deplatformer_webapp/static/assets/Facebook/Facebook-step2a.png
deplatformer_webapp/static/assets/Facebook/Facebook-step2b.png
deplatformer_webapp/static/assets/Facebook/Facebook-step3a.png
deplatformer_webapp/static/assets/Facebook/Facebook-step3b.png
deplatformer_webapp/static/assets/Facebook/Facebook-step3c.png
deplatformer_webapp/static/assets/deplatformr-border.png
deplatformer_webapp/static/assets/deplatformr-no-text-white.png
deplatformer_webapp/static/assets/deplatformr-no-text.png
deplatformer_webapp/static/assets/deplatformr-white-light.png
deplatformer_webapp/static/assets/deplatformr-white.png
deplatformer_webapp/static/assets/favicon.ico
deplatformer_webapp/static/assets/filecoin-logo.svg
deplatformer_webapp/static/assets/filecoin-logo2.svg
deplatformer_webapp/static/css/bootstrap.min.css
deplatformer_webapp-0.1.8.dist-info/entry_points.txt
deplatformer_webapp-0.1.8.dist-info/LICENSE
deplatformer_webapp-0.1.8.dist-info/WHEEL
deplatformer_webapp-0.1.8.dist-info/METADATA
deplatformer_webapp-0.1.8.dist-info/RECORD
